{"versions_info":{"1.28.7-1+deb11u2":null,"1.28.7-1":null,"1.28.7-1+deb11u1":null,"2.0rc2":["5d77cb51feec869c96ff4a525138163c7b72153b",1687299677.0],"2.0b1":["25317c17bebccaa33f66f2068e57baebb92f5a8e",1668773613.0],"2.0b2":["9762120c808e6ac643263fbc38e5d237256d7f44",1673220327.0],"2.0.1":["abadd2bc3347b09559c02b7cc264f3400a7cd63a",1723678564.0],"2.0rc1":["59672f652fc5e742aac699daa0babf41677aac44",1681296695.0],"2.0.0":["9c40967888b5a99ead2aa226b8a6dc7c959a9d83",1695402752.0],"2.0b3":["bdc5ae945ed0725e7a3806de7425c88a1e97834e",1675210314.0],"2.0b4":["f39d00bea568ebd71e47b4cc4c09cfd701b4e336",1678975122.0],"release-1-0-50":null,"release-1-14-1":null,"release-1-17.0":null,"release-1-0-34":null,"release-1-26-0":null,"release-1-0-45":null,"v1.17.9":null,"release-1-0-73":null,"release-1-20-0":null,"release-1-25-0":null,"release-1-0-67":null,"release-1-12-0":null,"release-1-0-40":null,"release-1-0-42":null,"release-1-0-1":null,"release-1-11-3":null,"release-1-15-0":null,"release-1-0-52":null,"release-1-0-33":null,"release-1-0-46":null,"release-1-13-3":null,"release-1-21-2":null,"release-1-25-10":null,"release-1-0-10":null,"release-1-0-74":null,"release-1-17-7":null,"release-1-0-72":null,"release-1-0-b1":null,"release-1-0-30":null,"release-1-3-0":null,"release-1-0-62":null,"release-1-20-4":null,"release-1-21-6":null,"release-1-0-71":null,"release-1-27-3":null,"release-1-21-0":null,"release-1-0-14":null,"release-1-0-75":null,"release-1-27-5":null,"release-1-0-22":null,"release-1-24-0":null,"release-1-22-4":null,"release-1-4-0":null,"release-1-0-68":null,"release-1-7-0":null,"release-1-20-2":null,"release-1-0-15":null,"release-1-21-4":null,"release-1-8-3":null,"release-1-11-0":null,"release-1-13-2":null,"release-1-0-48":null,"release-1-13-0":null,"release-1-17-4":null,"release-1-22-2":null,"release-1-16-1":null,"release-1-0-7":null,"release-1-6-0":null,"release-1-0-29":null,"release-1-0-6":null,"release-1-25-1":null,"release-1-27-1":null,"release-1-18-0":null,"release-1-0-13":null,"release-1-25-13":null,"release-1-26-1":null,"release-1-19-0":null,"release-1-0-76":null,"release-1-0-39":null,"release-1-11-5":null,"release-1-17-1":null,"release-1-17-9":null,"release-1-0-49":null,"release-1-0-61":null,"release-1-27-4":null,"release-1-17-2":null,"release-1-20-3":null,"release-1-0-53":null,"release-1-16-0":null,"release-1-0-54":null,"release-1-5-0":null,"release-1-0-51":null,"release-1-21-1":null,"release-1-0-23":null,"release-1-0-4":null,"release-1-0-12":null,"release-1-22-0":null,"release-1-0-69":null,"release-1-0-60":null,"release-1-22-5":null,"release-1-0-28":null,"release-1-23-0":null,"release-1-27-0":null,"release-1-25-12":null,"release-1-0-55":null,"release-1-0-21":null,"release-1-17-8":null,"release-1-0-5":null,"release-1-0-66":null,"release-1-0-70":null,"release-1-25-5":null,"release-1-0-59":null,"release-1-27-2":null,"release-1-0-9":null,"release-1-25-3":null,"release-1-25-4":null,"release-1-0":null,"release-1-25-9":null,"release-1-25-11":null,"release-1-9-0":null,"release-1-22-3":null,"release-1-13-4":null,"release-1-0-47":null,"release-1-0-41":null,"release-1-0-18":null,"release-1-16-4":null,"release-1-0-35":null,"release-1-0-19":null,"release-1-10-0":null,"release-1-16-2":null,"release-1-0-26":null,"release-1-13-5":null,"release-1-0-43":null,"release-1-0-17":null,"release-1-20-1":null,"release-1-11-4":null,"release-1-0-65":null,"release-1-14-0":null,"release-1-13-1":null,"release-1-0-16":null,"release-1-8-0":null,"release-1-11-2":null,"release-1-2-0":null,"release-1-0-3":null,"release-1-0-25":null,"release-1-0-63":null,"release-1-0-32":null,"2.1b1":null,"release-1-0-31":null,"release-1-0-11":null,"release-1-26-2":null,"release-1-25-2":null,"release-1-8-2":null,"release-1-1-0":null,"release-1-0-20":null,"release-1-0-8":null,"release-1-0-24":null,"release-1-0-58":null,"release-1-0-38":null,"release-1-25-8":null,"release-1-11-6":null,"release-1-25-6":null,"release-1-21-3":null,"release-1-17-5":null,"release-1-0-57":null,"release-1-25-7":null,"release-1-0-37":null,"release-1-0-44":null,"release-1-17-3":null,"release-1-0-2":null,"release-1-22-1":null,"release-1-17-6":null,"release-1-16-3":null,"release-1-0-56":null,"release-1-11-1":null,"release-1-21-5":null,"release-1-0-36":null,"release-1-22-6":null,"release-1-8-1":null,"release-1-0-27":null,"2.1.1":["089450357e61673fa9871b927c4b3b6cea4690a1",1736342783.0],"2.1.0":["ec1079c31ebebe720e645b19668f4f0800700e69",1729206882.0]},"hitting_set_results":{"8e6c787252a46fb6935d27fffd2e67de":["2.0.1"],"92cd39be971ecbcd10924a82acd7ed4a":["2.0.0"],"9a86c508f8c7d0c219b97de194805bcc":["2.0b1"],"1d5648fc0cc2f2e11f036325cc966535":["2.0.1"],"e8c6b9501fdefe63a30670d76507ff02":["2.0.0"],"613ca1b0a44669255321ae3131a4d3e3":["2.0.0"],"8631904a08f8224bc7b82bc1d28eaf5e":["2.0.1"]}}
