{"versions_info":{"1.3.1":["9cbae1d727b0201c32b743d759b4dfaa1bd9fdcd",1444313763.0],"1.5.0":["1512e185dfca8e7be6de4e2920bbb175d0d40c74",1524858558.0],"1.5.1":["cd494daddf3733eca4bfe2ccb54dcc1138760d92",1549532428.0],"1.0.0":["13f7d7c0fd2758079ea631a271d23bd4c398dc23",1415045516.0],"1.3.2":["f53badfabdee588e6792cc9518ed9b96cfe4b715",1446664044.0],"1.4.3":["d14196248100e694ed5c3353148e28fc6e5a5e90",1491242148.0],"1.3.5":["417d78c788638f455c10c56d8fe9c26cf7e68e69",1460564768.0],"1.5.2":["b275ba1cccb936f9387c78d6b953a76d2115ad7a",1568398397.0],"1.3.6":["2e3adc0c42c2b852dba2f8f9ffab2bc833e8dd3d",1463497300.0],"1.4.1":["4e9f339eaf884a3ed0c677462db3eb2e227adf2b",1465557811.0],"1.4.2":["84f0bbf161f4692488ffbe7dacfed07ee7b4c32c",1478190146.0],"1.3.4":["ed3cc5c2583e06374962eca62e87746d1e763fff",1452189945.0],"1.3.0":["72bf43150e17c176d175d526ca981e8d35fb51b4",1436280846.0],"1.1.0":["ead79b693a2ee0bb89a1602f8f89363d80d5ae9f",1424894806.0],"1.4.0":["aedb7949df43a61967495a82e9d7ce8833f1fe72",1464884558.0],"1.3.3":["42c6ca1938ae461797c114f6abd399bcec5bac1f",1451932172.0],"1.2.0":["44b58026eb425e89059428b5f74d059fc3d796b7",1432052045.0],"opennms-16.0.4-1":null,"opennms-24.0.0-1":null,"opennms-23.0.4-1":null,"meridian-foundation-2016.1.1-1":null,"opennms-25.1.0-1":null,"opennms-26.0.0-1":null,"opennms-17.1.0-1":null,"opennms-16.0.2-1":null,"opennms-25.2.1-1":null,"opennms-19.0.1-1":null,"meridian-foundation-2017.1.4-1":null,"opennms-25.1.2-1":null,"opennms-26.1.2-1":null,"opennms-16.0.0-1":null,"opennms-26.1.0-1":null,"opennms-27.0.0-1":null,"opennms-21.0.4-1":null,"opennms-25.0.0-1":null,"opennms-24.1.1-1":null,"opennms-18.0.1-1":null,"opennms-17.0.0-1":null,"opennms-27.0.2-1":null,"opennms-21.0.5-1":null,"opennms-20.1.0-1":null,"opennms-23.0.1-1":null,"meridian-foundation-2017.1.0-1":null,"opennms-26.2.2-1":null,"meridian-foundation-2015.1.4-1":null,"opennms-24.1.0-1":null,"opennms-21.0.0-1":null,"opennms-24.1.3-1":null,"meridian-foundation-2015.1.10-1":null,"meridian-foundation-2017.1.10-1":null,"opennms-20.0.1-1":null,"opennms-18.0.3-1":null,"opennms-25.1.1-1":null,"meridian-foundation-2015.1.3-1":null,"opennms-26.1.1-1":null,"meridian-foundation-2015.1.2-1":null,"opennms-26.1.3-1":null,"opennms-22.0.2-1":null,"meridian-foundation-2016.1.5-1":null,"meridian-foundation-2016.1.2-1":null,"meridian-foundation-2017.1.2-1":null,"opennms-22.0.0-1":null,"meridian-foundation-2016.1.6-1":null,"meridian-foundation-2017.1.5-1":null,"opennms-27.0.3-1":null,"opennms-21.0.1-1":null,"opennms-19.1.0-1":null,"opennms-25.2.0-1":null,"opennms-26.0.1-1":null,"meridian-foundation-2015.1.6-1":null,"meridian-foundation-2016.1.3-1":null,"opennms-19.0.0-1":null,"meridian-foundation-2016.1.9-1":null,"opennms-27.0.1-1":null,"opennms-16.0.1-1":null,"opennms-26.2.0-1":null,"meridian-foundation-2016.1.10-1":null,"opennms-17.1.1-1":null,"opennms-17.1.1-3":null,"opennms-23.0.0-1":null,"opennms-22.0.1-1":null,"opennms-26.2.1-1":null,"opennms-18.0.0-1":null,"opennms-22.0.3-1":null,"opennms-21.0.3-1":null,"meridian-foundation-2016.1.15-1":null,"opennms-23.0.2-1":null,"meridian-foundation-2015.1.7-1":null,"opennms-20.0.2-1":null,"opennms-23.0.3-1":null,"meridian-foundation-2016.1.4-1":null,"opennms-18.0.2-1":null,"meridian-foundation-2015.1.5-1":null,"opennms-22.0.4-1":null,"meridian-foundation-2015.1.1-1":null,"opennms-16.0.3-1":null,"opennms-24.1.2-1":null,"opennms-20.0.0-1":null,"meridian-foundation-2016.1.7-1":null,"opennms-18.0.4-1":null,"opennms-21.1.0-1":null,"meridian-foundation-2017.1.3-1":null,"opennms-17.1.1-2":null,"opennms-21.0.2-1":null,"meridian-foundation-2018.1.13-1":null,"meridian-foundation-2017.1.21-1":null,"meridian-foundation-2020.1.2-1":null,"meridian-foundation-2019.1.13-1":null,"meridian-foundation-2016.1.19-1":null,"meridian-foundation-2018.1.8-1":null,"meridian-foundation-2018.1.11-1":null,"meridian-foundation-2018.1.23-1":null,"meridian-foundation-2019.1.14-1":null,"meridian-foundation-2016.1.16-1":null,"meridian-foundation-2017.1.19-1":null,"meridian-foundation-2018.1.9-1":null,"meridian-foundation-2016.1.18-1":null,"meridian-foundation-2017.1.13-1":null,"meridian-foundation-2018.1.12-1":null,"meridian-foundation-2019.1.12-1":null,"meridian-foundation-2020.1.1-1":null,"meridian-foundation-2019.1.8-1":null,"meridian-foundation-2018.1.7-1":null,"meridian-foundation-2017.1.7-1":null,"meridian-foundation-2018.1.10-1":null,"meridian-foundation-2017.1.22-1":null,"meridian-foundation-2017.1.6-1":null,"meridian-foundation-2018.1.24-1":null,"meridian-foundation-2017.1.9-1":null,"space-integration-12.2-code-freeze":null,"meridian-foundation-2018.1.20-1":null,"meridian-foundation-2018.1.4-1":null,"meridian-foundation-2017.1.16-1":null,"meridian-foundation-2017.1.12-1":null,"meridian-foundation-2019.1.4-1":null,"meridian-foundation-2016.1.13-1":null,"opennms-1.9.0-1":null,"opennms-1.13.2-1":null,"meridian-foundation-2018.1.0-1":null,"meridian-foundation-2016.1.14-1":null,"opennms-1.11.3-1":null,"meridian-foundation-2016.1.21-1":null,"meridian-foundation-2016.1.11-1":null,"meridian-foundation-2018.1.14-1":null,"meridian-foundation-2016.1.12-1":null,"meridian-foundation-2016.1.8-1":null,"meridian-foundation-2018.1.22-1":null,"meridian-foundation-2018.1.21-1":null,"meridian-foundation-2019.1.7-1":null,"meridian-foundation-2017.1.24-1":null,"meridian-foundation-2016.1.20-1":null,"meridian-foundation-2020.1.0-1":null,"meridian-foundation-2017.1.18-1":null,"meridian-foundation-2019.1.10-1":null,"meridian-foundation-2018.1.18-1":null,"meridian-foundation-2018.1.16-1":null,"meridian-foundation-2018.1.17-1":null,"meridian-foundation-2019.1.1-1":null,"meridian-foundation-2018.1.19-1":null,"meridian-foundation-2017.1.26-1":null,"meridian-foundation-2017.1.11-1":null,"meridian-foundation-2019.1.15-1":null,"meridian-foundation-2018.1.6-1":null,"meridian-foundation-2019.1.11-1":null,"meridian-foundation-2018.1.2-1":null,"meridian-foundation-2020.1.4-1":null,"meridian-foundation-2017.1.14-1":null,"meridian-foundation-2019.1.5-1":null,"meridian-foundation-2016.1.23-1":null,"meridian-foundation-2018.1.15-1":null,"meridian-foundation-2016.1.17-1":null,"meridian-foundation-2019.1.0-1":null,"meridian-foundation-2017.1.17-1":null,"meridian-foundation-2018.1.3-1":null,"opennms-1.11.1-1":null,"meridian-foundation-2019.1.2-1":null,"meridian-foundation-2017.1.23-1":null,"meridian-foundation-2017.1.15-1":null,"meridian-foundation-2018.1.5-1":null,"meridian-foundation-2019.1.3-1":null,"meridian-foundation-2016.1.24-1":null,"opennms-1.9.93-1":null,"meridian-foundation-2017.1.20-1":null,"meridian-foundation-2018.1.1-1":null,"meridian-foundation-2019.1.6-1":null,"meridian-foundation-2017.1.25-1":null,"opennms-1.9.4-1":null,"meridian-foundation-2020.1.3-1":null,"meridian-foundation-2016.1.22-1":null,"meridian-foundation-2017.1.1-1":null,"meridian-foundation-2017.1.8-1":null},"hitting_set_results":{"6389360a9c7b79448836cbf30281ad1f":["1.5.2"]}}
